{
  "version": 1,
  "positions": {
    "1": {
      "x": 16,
      "y": 170
    },
    "2": {
      "x": 132,
      "y": 170
    },
    "3": {
      "x": 248,
      "y": 170
    },
    "4": {
      "x": 364,
      "y": 170
    },
    "5": {
      "x": 480,
      "y": 170
    },
    "6": {
      "x": 480,
      "y": 274
    },
    "7": {
      "x": 480,
      "y": 378
    },
    "8": {
      "x": 480,
      "y": 66
    },
    "9": {
      "x": 364,
      "y": 378
    },
    "10": {
      "x": 248,
      "y": 378
    },
    "11": {
      "x": 248,
      "y": 274
    },
    "12": {
      "x": 364,
      "y": 274
    },
    "13": {
      "x": 16,
      "y": 274
    },
    "14": {
      "x": 16,
      "y": 66
    },
    "15": {
      "x": 16,
      "y": 482
    },
    "16": {
      "x": 248,
      "y": -38
    },
    "17": {
      "x": 248,
      "y": 482
    },
    "20": {
      "x": 132,
      "y": 482
    },
    "21": {
      "x": 248,
      "y": 586
    },
    "22": {
      "x": 364,
      "y": 482
    },
    "23": {
      "x": 596,
      "y": 586
    },
    "24": {
      "x": 132,
      "y": 586
    },
    "25": {
      "x": 16,
      "y": 586
    },
    "26": {
      "x": 596,
      "y": 482
    },
    "27": {
      "x": 596,
      "y": 378
    },
    "28": {
      "x": 596,
      "y": 170
    },
    "48": {
      "x": 596,
      "y": 66
    },
    "49": {
      "x": 596,
      "y": -38
    },
    "50": {
      "x": 480,
      "y": -38
    }
  }
}
